cookie_composer/__init__.py
cookie_composer/authentication.py
cookie_composer/cc_overrides.py
cookie_composer/cli.py
cookie_composer/composition.py
cookie_composer/data_merge.py
cookie_composer/diff.py
cookie_composer/exceptions.py
cookie_composer/git_commands.py
cookie_composer/io.py
cookie_composer/layers.py
cookie_composer/matching.py
cookie_composer/utils.py
cookie_composer/commands/__init__.py
cookie_composer/commands/add.py
cookie_composer/commands/authn.py
cookie_composer/commands/create.py
cookie_composer/commands/link.py
cookie_composer/commands/update.py
cookie_composer/merge_files/__init__.py
cookie_composer/merge_files/ini_file.py
cookie_composer/merge_files/json_file.py
cookie_composer/merge_files/toml_file.py
cookie_composer/merge_files/yaml_file.py
cookie_composer/templates/__init__.py
cookie_composer/templates/git_repo.py
cookie_composer/templates/source.py
cookie_composer/templates/types.py
cookie_composer/templates/zipfile_repo.py
cookie_composer-0.13.1.dist-info/LICENSE
cookie_composer-0.13.1.dist-info/METADATA
cookie_composer-0.13.1.dist-info/WHEEL
cookie_composer-0.13.1.dist-info/entry_points.txt
cookie_composer-0.13.1.dist-info/top_level.txt
cookie_composer-0.13.1.dist-info/RECORD
