Metadata-Version: 2.1
Name: cookie-composer
Version: 0.13.1
Summary: Create new projects from a composition of several templates
Author-email: Corey Oordt <coreyoordt@gmail.com>
License: BSD-3-Clause
Project-URL: Homepage, https://github.com/callowayproject/cookie-composer
Project-URL: Documentation, https://callowayproject.github.io/cookie-composer/
Keywords: cookie-composer,cookiecutter,scaffold
Classifier: Development Status :: 4 - Beta
Classifier: Environment :: Console
Classifier: Intended Audience :: Developers
Classifier: Natural Language :: English
Classifier: License :: OSI Approved :: BSD License
Classifier: Programming Language :: Python :: 3.8
Classifier: Programming Language :: Python :: 3.9
Classifier: Programming Language :: Python :: 3.10
Classifier: Programming Language :: Python :: 3.11
Classifier: Topic :: Software Development
Classifier: Topic :: Software Development :: Code Generators
Requires-Python: >=3.8
License-File: LICENSE
Requires-Dist: click-log
Requires-Dist: cookiecutter ==2.6.0
Requires-Dist: fsspec[http]
Requires-Dist: ghapi
Requires-Dist: gitpython >=3.1.37
Requires-Dist: immutabledict
Requires-Dist: orjson
Requires-Dist: pydantic >2.0.0
Requires-Dist: questionary
Requires-Dist: requests
Requires-Dist: rich-click
Requires-Dist: ruamel.yaml
Requires-Dist: toml
Provides-Extra: dev
Requires-Dist: bump-my-version >=0.11.0 ; extra == 'dev'
Requires-Dist: git-fame >=1.12.2 ; extra == 'dev'
Requires-Dist: generate-changelog ; extra == 'dev'
Requires-Dist: pip-tools ; extra == 'dev'
Provides-Extra: docs
Requires-Dist: black ; extra == 'docs'
Requires-Dist: markdown-customblocks ; extra == 'docs'
Requires-Dist: mdx-truly-sane-lists ; extra == 'docs'
Requires-Dist: mkdocs ; extra == 'docs'
Requires-Dist: mkdocs-click ; extra == 'docs'
Requires-Dist: mkdocs-drawio ; extra == 'docs'
Requires-Dist: mkdocs-gen-files ; extra == 'docs'
Requires-Dist: mkdocs-git-authors-plugin ; extra == 'docs'
Requires-Dist: mkdocs-git-committers-plugin ; extra == 'docs'
Requires-Dist: mkdocs-git-revision-date-localized-plugin ; extra == 'docs'
Requires-Dist: mkdocs-include-markdown-plugin ; extra == 'docs'
Requires-Dist: mkdocs-literate-nav ; extra == 'docs'
Requires-Dist: mkdocs-material ; extra == 'docs'
Requires-Dist: mkdocstrings[python] ; extra == 'docs'
Requires-Dist: python-frontmatter ; extra == 'docs'
Requires-Dist: pyyaml ; extra == 'docs'
Provides-Extra: test
Requires-Dist: coverage >=6.1.2 ; extra == 'test'
Requires-Dist: pre-commit >=2.15.0 ; extra == 'test'
Requires-Dist: pytest-cov >=3.0.0 ; extra == 'test'
Requires-Dist: pytest-env ; extra == 'test'
Requires-Dist: pytest-mock ; extra == 'test'
Requires-Dist: pytest >=6.0.0 ; extra == 'test'
